merlinwf/__init__.py
merlinwf/main.py
merlinwf-2.0.1.dist-info/METADATA
merlinwf-2.0.1.dist-info/WHEEL
merlinwf-2.0.1.dist-info/entry_points.txt
merlinwf-2.0.1.dist-info/top_level.txt
merlinwf-2.0.1.dist-info/RECORD
