Metadata-Version: 2.1
Name: merlinwf
Version: 2.0.1
Summary: The 'merlinwf' package has been deprecated and replaced by the 'merlin' package.
Home-page: https://github.com/LLNL/merlin
Author: Merlin Dev team
Author-email: merlin@llnl.gov
License: MIT
Platform: UNKNOWN
Classifier: Programming Language :: Python :: 3.6
Classifier: Programming Language :: Python :: 3.7
Classifier: Programming Language :: Python :: 3.8
Classifier: Programming Language :: Python :: 3.9
